jsp_shaving1996/__init__.py
jsp_shaving1996/main.py
jsp_shaving1996/test.ipynb
jsp_shaving1996/utils/__init__.py
jsp_shaving1996/utils/backward.py
jsp_shaving1996/utils/feasibility.py
jsp_shaving1996/utils/forward.py
jsp_shaving1996/utils/jsp.py
jsp_shaving1996-0.1.51.dist-info/WHEEL
jsp_shaving1996-0.1.51.dist-info/METADATA
jsp_shaving1996-0.1.51.dist-info/RECORD
