Metadata-Version: 2.1
Name: jsp-shaving1996
Version: 0.1.51
Summary: P, Martin.らの1996年の論文のshavingを実装したもの
Home-page: https://github.com/tkp0331/jsp-shaving1996
Author: 鈴木貴大
Author-email: merioda.seven.24@gmail.com
Requires-Python: >=3.7.9,<4.0.0
Classifier: Programming Language :: Python :: 3
Classifier: Programming Language :: Python :: 3.10
Classifier: Programming Language :: Python :: 3.8
Classifier: Programming Language :: Python :: 3.9
Requires-Dist: jsp-exp (>=0.1.31,<0.2.0)
Requires-Dist: jsp-shaving1990 (>=0.1.51,<0.2.0)
Project-URL: Repository, https://github.com/tkp0331/jsp-shaving1996
